pydanticscim/__init__.py
pydanticscim/enterprise_user.py
pydanticscim/group.py
pydanticscim/resource_type.py
pydanticscim/responses.py
pydanticscim/service_provider.py
pydanticscim/user.py
pydantic_scim-0.0.8.dist-info/LICENSE
pydantic_scim-0.0.8.dist-info/METADATA
pydantic_scim-0.0.8.dist-info/WHEEL
pydantic_scim-0.0.8.dist-info/top_level.txt
pydantic_scim-0.0.8.dist-info/RECORD
