Metadata-Version: 2.1
Name: pydantic-scim
Version: 0.0.8
Summary: Pydantic types for SCIM
Home-page: https://chalk.ai
Author: Chalk AI, Inc.
Classifier: Programming Language :: Python
Classifier: Programming Language :: Python :: 3
Classifier: Programming Language :: Python :: 3.8
Requires-Python: >=3.8.0
License-File: LICENSE
Requires-Dist: pydantic >=1.8.0
Requires-Dist: pydantic[email] >=1.8.0
